[
  {
    "gameId": "2025-W01-DAL-PHI",
    "homeScore": 24,
    "awayScore": 20,
    "status": "final",
    "network": "NBC"
  },
  {
    "gameId": "2025-W01-KC-LAC",
    "homeScore": 27,
    "awayScore": 21,
    "status": "final",
    "network": "AMZN"
  },
  {
    "gameId": "2025-W01-NYG-WAS",
    "homeScore": 21,
    "awayScore": 6,
    "status": "final"
  },
  {
    "gameId": "2025-W01-TB-ATL",
    "homeScore": 20,
    "awayScore": 23,
    "status": "final"
  },
  {
    "gameId": "2025-W01-CAR-JAX",
    "homeScore": 26,
    "awayScore": 10,
    "status": "final"
  },
  {
    "gameId": "2025-W01-MIA-IND",
    "homeScore": 33,
    "awayScore": 8,
    "status": "final"
  },
  {
    "gameId": "2025-W01-LV-NE",
    "homeScore": 13,
    "awayScore": 20,
    "status": "final"
  },
  {
    "gameId": "2025-W01-PIT-NYJ",
    "homeScore": 32,
    "awayScore": 34,
    "status": "final"
  },
  {
    "gameId": "2025-W01-CIN-CLE",
    "homeScore": 16,
    "awayScore": 17,
    "status": "final"
  },
  {
    "gameId": "2025-W01-ARI-NO",
    "homeScore": 13,
    "awayScore": 20,
    "status": "final"
  },
  {
    "gameId": "2025-W01-SF-SEA",
    "homeScore": 13,
    "awayScore": 17,
    "status": "final"
  },
  {
    "gameId": "2025-W01-TEN-DEN",
    "homeScore": 20,
    "awayScore": 12,
    "status": "final"
  },
  {
    "gameId": "2025-W01-DET-GB",
    "homeScore": 27,
    "awayScore": 13,
    "status": "final"
  },
  {
    "gameId": "2025-W01-HOU-LAR",
    "homeScore": 14,
    "awayScore": 9,
    "status": "final"
  },
  {
    "gameId": "2025-W01-BAL-BUF",
    "homeScore": 7,
    "awayScore": 10,
    "status": "live",
    "quarter": 2,
    "timeRemaining": "3:22",
    "possession": "BUF",
    "network": "CBS"
  },
  {
    "gameId": "2025-W01-MIN-CHI",
    "homeScore": 14,
    "awayScore": 10,
    "status": "live",
    "quarter": 3,
    "timeRemaining": "8:45",
    "possession": "MIN"
  }
]